stakeout/__init__.py
stakeout/main.py
stakeout/stakeout.py
stakeout-1.0.2.dist-info/LICENSE
stakeout-1.0.2.dist-info/METADATA
stakeout-1.0.2.dist-info/WHEEL
stakeout-1.0.2.dist-info/entry_points.txt
stakeout-1.0.2.dist-info/top_level.txt
stakeout-1.0.2.dist-info/RECORD
