Metadata-Version: 2.1
Name: stakeout
Version: 1.0.2
Summary: A tool to inspect source code ownership.
Author-email: Dmitry Zolotaryov <dmitry@zolotaryov.com>
Project-URL: Homepage, https://github.com/dmitry-zolotaryov/stakeout
Project-URL: Issues, https://github.com/dmitry-zolotaryov/stakeout/issues
Requires-Python: >=3.10
License-File: LICENSE
